osut/__init__.py
osut/osut.py
osut-0.8.1.dist-info/licenses/LICENSE
osut-0.8.1.dist-info/METADATA
osut-0.8.1.dist-info/WHEEL
osut-0.8.1.dist-info/top_level.txt
osut-0.8.1.dist-info/RECORD
