Metadata-Version: 2.4
Name: osut
Version: 0.8.1
Summary: OpenStudio SDK utilities for Python
Author-email: Denis Bourgeois <denis@rd2.ca>
Maintainer-email: Denis Bourgeois <denis@rd2.ca>
License-Expression: BSD-3-Clause
Project-URL: Homepage, https://github.com/rd2/pyOSut
Project-URL: Bug Tracker, https://github.com/rd2/pyOSut/issues
Keywords: openstudio,utilities
Classifier: Programming Language :: Python :: 3.2
Classifier: Intended Audience :: Developers
Classifier: Topic :: Software Development :: Libraries :: Python Modules
Classifier: Operating System :: OS Independent
Requires-Python: >=3.2
License-File: LICENSE
Requires-Dist: oslg
Dynamic: license-file
